fsm_admin_lite/__init__.py
fsm_admin_lite/mixins.py
fsm_admin_lite/templates/admin/fsm_admin_change_form.html
django_fsm_admin_lite-0.1.0.dist-info/LICENSE
django_fsm_admin_lite-0.1.0.dist-info/WHEEL
django_fsm_admin_lite-0.1.0.dist-info/METADATA
django_fsm_admin_lite-0.1.0.dist-info/RECORD
