Metadata-Version: 2.1
Name: django-fsm-admin-lite
Version: 0.1.0
Summary: Integrate django-fsm state transitions into Django Admin.
Home-page: https://github.com/etchegom/django-fsm-admin-lite
License: MIT
Keywords: django,fsm
Author: Matthieu Etchegoyen
Author-email: etchegom@gmail.com
Maintainer: Matthieu Etchegoyen
Maintainer-email: etchegom@gmail.com
Requires-Python: >=3.8,<4.0
Classifier: Environment :: Web Environment
Classifier: Framework :: Django
Classifier: Framework :: Django :: 3.2
Classifier: Framework :: Django :: 4
Classifier: Framework :: Django :: 4.0
Classifier: Framework :: Django :: 4.1
Classifier: Intended Audience :: Developers
Classifier: License :: OSI Approved :: MIT License
Classifier: Natural Language :: English
Classifier: Operating System :: OS Independent
Classifier: Programming Language :: Python :: 3
Classifier: Programming Language :: Python :: 3.8
Classifier: Programming Language :: Python :: 3.9
Classifier: Programming Language :: Python :: 3.10
Classifier: Programming Language :: Python :: 3.11
Classifier: Programming Language :: Python :: 3
Classifier: Programming Language :: Python :: 3 :: Only
Classifier: Programming Language :: Python :: 3.10
Classifier: Programming Language :: Python :: 3.8
Classifier: Programming Language :: Python :: 3.9
Requires-Dist: django (>=3.2,<5.0)
Requires-Dist: django-fsm (>=2.8.1,<3.0.0)
Project-URL: Documentation, https://github.com/etchegom/django-fsm-admin-lite
Project-URL: Repository, https://github.com/etchegom/django-fsm-admin-lite
